README.txt
setup.cfg
setup.py
docs/HISTORY.txt
raptus/__init__.py
raptus.backlink.egg-info/PKG-INFO
raptus.backlink.egg-info/SOURCES.txt
raptus.backlink.egg-info/dependency_links.txt
raptus.backlink.egg-info/entry_points.txt
raptus.backlink.egg-info/namespace_packages.txt
raptus.backlink.egg-info/not-zip-safe
raptus.backlink.egg-info/requires.txt
raptus.backlink.egg-info/top_level.txt
raptus/backlink/__init__.py
raptus/backlink/configure.zcml
raptus/backlink/browser/__init__.py
raptus/backlink/browser/back.pt
raptus/backlink/browser/back.py
raptus/backlink/browser/configure.zcml
raptus/backlink/i18n/raptus.backlink-de.po
raptus/backlink/i18n/raptus.backlink-fr.po
raptus/backlink/i18n/raptus.backlink.pot
raptus/backlink/profiles/default/cssregistry.xml
raptus/backlink/profiles/default/metadata.xml
raptus/backlink/profiles/default/skins.xml
raptus/backlink/profiles/default/viewlets.xml
raptus/backlink/skins/raptus_backlink/raptus.backlink.css.dtml